huntsman/__init__.py
huntsman/__main__.py
huntsman/commands_hunterio/__init__.py
huntsman/commands_hunterio/account_info.py
huntsman/commands_hunterio/confirm_context.py
huntsman/commands_hunterio/confirm_user.py
huntsman/commands_hunterio/domain_search.py
huntsman/commands_hunterio/email_count.py
huntsman/commands_hunterio/email_finder.py
huntsman/commands_hunterio/email_verifier.py
huntsman/commands_skrappio/__init__.py
huntsman/commands_skrappio/account_data.py
huntsman/commands_skrappio/company_search.py
huntsman/commands_snovio/__init__.py
huntsman/commands_snovio/domain_searchv2.py
huntsman/commands_snovio/email_count.py
huntsman/commands_snovio/email_verifier.py
huntsman/commands_snovio/get_balance.py
huntsman/commands_snovio/get_profile.py
huntsman/utils/__init__.py
huntsman/utils/helpers.py
huntsman/utils/user_enum.py
huntsman/utils/user_gen.py
huntsman-0.5.2.dist-info/LICENSE
huntsman-0.5.2.dist-info/METADATA
huntsman-0.5.2.dist-info/WHEEL
huntsman-0.5.2.dist-info/entry_points.txt
huntsman-0.5.2.dist-info/top_level.txt
huntsman-0.5.2.dist-info/RECORD
