Metadata-Version: 2.1
Name: huntsman
Version: 0.5.2
Summary: Email enumerator, validator, and username generator for the hunter.io, snov.io, and skrapp.io APIs
Home-page: https://github.com/mlcsec/huntsman
Author: mlcsec
Author-email: mlcsec <mlcsec@proton.me>
Project-URL: Homepage, https://github.com/mlcsec/huntsman
Classifier: Programming Language :: Python :: 3
Classifier: License :: OSI Approved :: MIT License
Classifier: Operating System :: OS Independent
Classifier: Development Status :: 3 - Alpha
Classifier: Intended Audience :: Developers
Classifier: Intended Audience :: Information Technology
Classifier: Topic :: Security
Requires-Python: >=3.6
License-File: LICENSE
